bluetooth_numbers/__init__.py
bluetooth_numbers/_characteristics.py
bluetooth_numbers/_companies.py
bluetooth_numbers/_descriptors.py
bluetooth_numbers/_ouis.py
bluetooth_numbers/_services.py
bluetooth_numbers/dicts.py
bluetooth_numbers/exceptions.py
bluetooth_numbers/py.typed
bluetooth_numbers/reverse_lookup.py
bluetooth_numbers/utils.py
bluetooth_numbers-1.1.2.dist-info/LICENSE.txt
bluetooth_numbers-1.1.2.dist-info/METADATA
bluetooth_numbers-1.1.2.dist-info/WHEEL
bluetooth_numbers-1.1.2.dist-info/top_level.txt
bluetooth_numbers-1.1.2.dist-info/RECORD
