Metadata-Version: 2.1
Name: bluetooth-numbers
Version: 1.1.2
Summary: Python package with a wide set of numbers related to Bluetooth
Home-page: https://github.com/koenvervloesem/bluetooth-numbers
Author: Koen Vervloesem
Author-email: koen@vervloesem.eu
License: MIT
Project-URL: Documentation, https://bluetooth-numbers.readthedocs.io/
Project-URL: Source, https://github.com/koenvervloesem/bluetooth-numbers
Project-URL: Changelog, https://github.com/koenvervloesem/bluetooth-numbers/blob/main/CHANGELOG.rst
Project-URL: Tracker, https://github.com/koenvervloesem/bluetooth-numbers/issues
Project-URL: Download, https://pypi.org/project/bluetooth-numbers/#files
Keywords: bluetooth,ble,bluetooth-low-energy,uuids,oui,assigned-numbers,services,characteristics,descriptors
Platform: any
Classifier: Development Status :: 4 - Beta
Classifier: Intended Audience :: Developers
Classifier: License :: OSI Approved :: MIT License
Classifier: Programming Language :: Python
Classifier: Programming Language :: Python :: 3
Classifier: Programming Language :: Python :: 3 :: Only
Classifier: Programming Language :: Python :: 3.8
Classifier: Programming Language :: Python :: 3.9
Classifier: Programming Language :: Python :: 3.10
Classifier: Programming Language :: Python :: 3.11
Classifier: Programming Language :: Python :: 3.12
Classifier: Topic :: Software Development :: Libraries
Classifier: Topic :: Software Development :: Libraries :: Python Modules
Requires-Python: >=3.8
License-File: LICENSE.txt
Provides-Extra: testing
Requires-Dist: setuptools ; extra == 'testing'
Requires-Dist: pytest ; extra == 'testing'
Requires-Dist: pytest-cov ; extra == 'testing'
